odoo/addons/shopinvader_product_price_tax/README.rst
odoo/addons/shopinvader_product_price_tax/__init__.py
odoo/addons/shopinvader_product_price_tax/__manifest__.py
odoo/addons/shopinvader_product_price_tax/i18n/shopinvader_product_price_tax.pot
odoo/addons/shopinvader_product_price_tax/models/__init__.py
odoo/addons/shopinvader_product_price_tax/models/shopinvader_variant.py
odoo/addons/shopinvader_product_price_tax/readme/CONTRIBUTORS.rst
odoo/addons/shopinvader_product_price_tax/readme/DESCRIPTION.rst
odoo/addons/shopinvader_product_price_tax/static/description/index.html
odoo/addons/shopinvader_product_price_tax/tests/__init__.py
odoo/addons/shopinvader_product_price_tax/tests/test_product.py
odoo14_addon_shopinvader_product_price_tax-14.0.1.2.0.dist-info/METADATA
odoo14_addon_shopinvader_product_price_tax-14.0.1.2.0.dist-info/WHEEL
odoo14_addon_shopinvader_product_price_tax-14.0.1.2.0.dist-info/top_level.txt
odoo14_addon_shopinvader_product_price_tax-14.0.1.2.0.dist-info/RECORD
